{
  "_fv": 10,
  "_type": "mob",
  "definition": {
    "mobName": "Giant Spider",
    "mobLabel": "",
    "mobModelName": "Modelqueen_spider",
    "mobModelTexture": "giant_spider.png",
    "mobModelGlowTexture": "",
    "modelWidth": 2.2,
    "modelHeight": 1.0,
    "modelShadowSize": 0.5,
    "mountedYOffset": 0.0,
    "hasSpawnEgg": true,
    "spawnEggBaseColor": {
      "value": -14606047,
      "falpha": 0.0
    },
    "spawnEggDotColor": {
      "value": -5763570,
      "falpha": 0.0
    },
    "creativeTab": {
      "value": "MISC"
    },
    "isBoss": false,
    "bossBarColor": "PINK",
    "bossBarType": "PROGRESS",
    "equipmentMainHand": {
      "value": ""
    },
    "equipmentOffHand": {
      "value": ""
    },
    "equipmentHelmet": {
      "value": ""
    },
    "equipmentBody": {
      "value": ""
    },
    "equipmentLeggings": {
      "value": ""
    },
    "equipmentBoots": {
      "value": ""
    },
    "mobBehaviourType": "Mob",
    "mobCreatureType": "UNDEFINED",
    "attackStrength": 6,
    "movementSpeed": 0.3,
    "armorBaseValue": 0.0,
    "trackingRange": 64,
    "health": 50,
    "xpAmount": 4,
    "waterMob": false,
    "flyingMob": false,
    "guiBoundTo": "<NONE>",
    "inventorySize": 9,
    "inventoryStackSize": 64,
    "disableCollisions": false,
    "ridable": false,
    "canControlForward": false,
    "canControlStrafe": false,
    "immuneToFire": false,
    "immuneToArrows": false,
    "immuneToFallDamage": true,
    "immuneToCactus": false,
    "immuneToDrowning": false,
    "immuneToLightning": false,
    "immuneToPotions": false,
    "immuneToPlayer": false,
    "mobDrop": {
      "value": "Items.SPIDER_EYE"
    },
    "livingSound": {
      "value": "entity.spider.ambient"
    },
    "hurtSound": {
      "value": "entity.spider.hurt"
    },
    "deathSound": {
      "value": "entity.spider.death"
    },
    "stepSound": {
      "value": "entity.spider.step"
    },
    "spawnParticles": false,
    "particleToSpawn": {
      "value": "EXPLOSION_NORMAL"
    },
    "particleSpawningShape": "Spread",
    "particleSpawningRadious": 0.5,
    "particleAmount": 4,
    "onMobTickUpdate": {
      "name": "GiantSpiderOnEntityTickUpdate"
    },
    "onInitialSpawn": {
      "name": "GiantSpiderOnInitialEntitySpawn"
    },
    "hasAI": true,
    "aiBase": "Spider",
    "aixml": "<xml xmlns=\"https://developers.google.com/blockly/xml\"><block type=\"aitasks_container\" deletable=\"false\" x=\"40\" y=\"40\"><next><block type=\"attack_on_collide\"><field name=\"speed\">1.2</field><field name=\"longmemory\">FALSE</field><field name=\"condition\">null,null</field><next><block type=\"wander\"><field name=\"speed\">1</field><field name=\"condition\">null,null</field><next><block type=\"attack_action\"><field name=\"callhelp\">FALSE</field><field name=\"condition\">null,null</field><next><block type=\"look_around\"><field name=\"condition\">null,null</field><next><block type=\"swim_in_water\"><field name=\"condition\">null,null</field></block></next></block></next></block></next></block></next></block></next></block></xml>",
    "breedable": false,
    "tameable": false,
    "breedTriggerItems": [],
    "ranged": false,
    "rangedAttackItem": {
      "value": ""
    },
    "rangedItemType": "Default item",
    "spawnThisMob": true,
    "doesDespawnWhenIdle": true,
    "spawningProbability": 3,
    "mobSpawningType": "monster",
    "minNumberOfMobsPerGroup": 1,
    "maxNumberOfMobsPerGroup": 1,
    "restrictionBiomes": [
      {
        "value": "plains"
      },
      {
        "value": "desert"
      },
      {
        "value": "mountains"
      },
      {
        "value": "forest"
      },
      {
        "value": "taiga"
      },
      {
        "value": "swamp"
      },
      {
        "value": "snowy_tundra"
      },
      {
        "value": "snowy_mountains"
      },
      {
        "value": "beaches"
      },
      {
        "value": "desert_hills"
      },
      {
        "value": "forest_hills"
      },
      {
        "value": "taiga_hills"
      },
      {
        "value": "smaller_extreme_hills"
      },
      {
        "value": "jungle"
      },
      {
        "value": "jungle_hills"
      },
      {
        "value": "jungle_edge"
      },
      {
        "value": "birch_forest"
      },
      {
        "value": "birch_forest_hills"
      },
      {
        "value": "roofed_forest"
      },
      {
        "value": "taiga_cold"
      },
      {
        "value": "taiga_cold_hills"
      },
      {
        "value": "redwood_taiga"
      },
      {
        "value": "redwood_taiga_hills"
      },
      {
        "value": "extreme_hills_with_trees"
      },
      {
        "value": "savanna"
      },
      {
        "value": "savanna_rock"
      },
      {
        "value": "badlands"
      },
      {
        "value": "wooded_badlands_plateau"
      },
      {
        "value": "badlands_plateau"
      },
      {
        "value": "bamboo_jungle"
      },
      {
        "value": "bamboo_jungle_hills"
      }
    ],
    "spawnInDungeons": false
  }
}